NiukeGuanpeishengQiuzhiJingyanFenxiang20212022Fix1/README.md
NiukeGuanpeishengQiuzhiJingyanFenxiang20212022Fix1/__init__.py
NiukeGuanpeishengQiuzhiJingyanFenxiang20212022Fix1/__main__.py
NiukeGuanpeishengQiuzhiJingyanFenxiang20212022Fix1/file.epub
NiukeGuanpeishengQiuzhiJingyanFenxiang20212022Fix1/index.html
NiukeGuanpeishengQiuzhiJingyanFenxiang20212022Fix1/css/__init__.py
NiukeGuanpeishengQiuzhiJingyanFenxiang20212022Fix1/css/annotations.css
NiukeGuanpeishengQiuzhiJingyanFenxiang20212022Fix1/css/main.css
NiukeGuanpeishengQiuzhiJingyanFenxiang20212022Fix1/css/normalize.css
NiukeGuanpeishengQiuzhiJingyanFenxiang20212022Fix1/css/popup.css
NiukeGuanpeishengQiuzhiJingyanFenxiang20212022Fix1/font/__init__.py
NiukeGuanpeishengQiuzhiJingyanFenxiang20212022Fix1/font/fontello.eot
NiukeGuanpeishengQiuzhiJingyanFenxiang20212022Fix1/font/fontello.svg
NiukeGuanpeishengQiuzhiJingyanFenxiang20212022Fix1/font/fontello.ttf
NiukeGuanpeishengQiuzhiJingyanFenxiang20212022Fix1/font/fontello.woff
NiukeGuanpeishengQiuzhiJingyanFenxiang20212022Fix1/img/__init__.py
NiukeGuanpeishengQiuzhiJingyanFenxiang20212022Fix1/img/annotator-glyph-sprite.png
NiukeGuanpeishengQiuzhiJingyanFenxiang20212022Fix1/img/annotator-icon-sprite.png
NiukeGuanpeishengQiuzhiJingyanFenxiang20212022Fix1/img/apple-touch-icon.png
NiukeGuanpeishengQiuzhiJingyanFenxiang20212022Fix1/img/cancelfullscreen.png
NiukeGuanpeishengQiuzhiJingyanFenxiang20212022Fix1/img/close.png
NiukeGuanpeishengQiuzhiJingyanFenxiang20212022Fix1/img/fullscreen.png
NiukeGuanpeishengQiuzhiJingyanFenxiang20212022Fix1/img/loader.gif
NiukeGuanpeishengQiuzhiJingyanFenxiang20212022Fix1/img/menu-icon.png
NiukeGuanpeishengQiuzhiJingyanFenxiang20212022Fix1/img/save.png
NiukeGuanpeishengQiuzhiJingyanFenxiang20212022Fix1/img/saved.png
NiukeGuanpeishengQiuzhiJingyanFenxiang20212022Fix1/img/settings-s.png
NiukeGuanpeishengQiuzhiJingyanFenxiang20212022Fix1/img/settings.png
NiukeGuanpeishengQiuzhiJingyanFenxiang20212022Fix1/img/star.png
niuke_guanpeisheng_qiuzhi_jingyan_fenxiang_2021_2022_fix1-2025.3.25.0.dist-info/METADATA
niuke_guanpeisheng_qiuzhi_jingyan_fenxiang_2021_2022_fix1-2025.3.25.0.dist-info/WHEEL
niuke_guanpeisheng_qiuzhi_jingyan_fenxiang_2021_2022_fix1-2025.3.25.0.dist-info/entry_points.txt
niuke_guanpeisheng_qiuzhi_jingyan_fenxiang_2021_2022_fix1-2025.3.25.0.dist-info/top_level.txt
niuke_guanpeisheng_qiuzhi_jingyan_fenxiang_2021_2022_fix1-2025.3.25.0.dist-info/RECORD
